elastic_apm_asgi/__init__.py
elastic_apm_asgi/middleware.py
elastic_apm_asgi/version.py
elastic_apm_asgi-0.0.11.dist-info/METADATA
elastic_apm_asgi-0.0.11.dist-info/WHEEL
elastic_apm_asgi-0.0.11.dist-info/top_level.txt
elastic_apm_asgi-0.0.11.dist-info/RECORD
