Metadata-Version: 2.1
Name: elastic-apm-asgi
Version: 0.0.11
Summary: Elastic APM integration for ASGI frameworks.
Home-page: https://github.com/Mdslino/Elastic-APM-ASGI
Author: Marcelo Lino
Author-email: mdslino@gmail.com
License: BSD
Platform: UNKNOWN
Classifier: Development Status :: 3 - Alpha
Classifier: Environment :: Web Environment
Classifier: Intended Audience :: Developers
Classifier: License :: OSI Approved :: BSD License
Classifier: Operating System :: OS Independent
Classifier: Topic :: Internet :: WWW/HTTP
Classifier: Programming Language :: Python :: 3
Classifier: Programming Language :: Python :: 3.6
Classifier: Programming Language :: Python :: 3.7
Requires-Dist: elastic-apm
